README.md
setup.py
storified.py
storified.egg-info/PKG-INFO
storified.egg-info/SOURCES.txt
storified.egg-info/dependency_links.txt
storified.egg-info/requires.txt
storified.egg-info/top_level.txt