Metadata-Version: 1.0
Name: storified
Version: 0.0.9
Summary: Download your Storify data
Home-page: http://github.com/docnow/storified
Author: Ed Summers
Author-email: ehs@pobox.com
License: UNKNOWN
Platform: UNKNOWN
